Metadata-Version: 2.0
Name: odoo8-addon-l10n-es-aeat-mod340
Version: 8.0.2.5.1
Summary: Generación de fichero modelo 340 y libro de IVA
Home-page: https://github.com/OCA/l10n-spain
Author: Spanish Localization Team,Odoo Community Association (OCA), 
Author-email: support@odoo-community.org
License: AGPL-3
Platform: UNKNOWN
Classifier: Programming Language :: Python :: 2.7
Classifier: Framework :: Odoo
Classifier: License :: OSI Approved :: GNU Affero General Public License v3
Requires-Dist: odoo (<9.0a,>=8.0a)
Requires-Dist: odoo8-addon-account-chart-update
Requires-Dist: odoo8-addon-account-invoice-currency
Requires-Dist: odoo8-addon-account-refund-original
Requires-Dist: odoo8-addon-l10n-es-aeat
Requires-Dist: odoo8-addon-l10n-es-aeat-mod349
